cmdu/__init__.py
cmdu/__main__.py
cmdu/check_list/__init__.py
cmdu/check_list/check_list_item.py
cmdu/converter_json_yaml/__init__.py
cmdu/converter_json_yaml/json2yaml.py
cmdu/hosts/__init__.py
cmdu/hosts/hosts.py
cmdu/lines/__init__.py
cmdu/lines/cmd_set_nu.py
cmdu/lines/line_number.py
cmdu/test/__init__.py
cmdu/test/test_line/__init__.py
cmdu/test/test_line/test_line.py
cmdu-0.0.15.dist-info/METADATA
cmdu-0.0.15.dist-info/WHEEL
cmdu-0.0.15.dist-info/RECORD
